django_lair/__init__.py
django_lair/admin.py
django_lair/apps.py
django_lair/models.py
django_lair/urls.py
django_lair/util.py
django_lair/views.py
django_lair/migrations/0001_initial.py
django_lair/migrations/__init__.py
django_lair/templates/django_lair/base.html
django_lair/templates/django_lair/chart.html
django_lair/templates/django_lair/datum_detail.html
django_lair/templates/django_lair/datum_form.html
django_lair/templates/django_lair/datum_list.html
django_lair/templates/django_lair/datum_list_table.html
django_lair/templates/django_lair/user_detail.html
django_lair/tests/__init__.py
django_lair/tests/test_util.py
django_lair-1.0.3.dist-info/DESCRIPTION.rst
django_lair-1.0.3.dist-info/METADATA
django_lair-1.0.3.dist-info/RECORD
django_lair-1.0.3.dist-info/WHEEL
django_lair-1.0.3.dist-info/metadata.json
django_lair-1.0.3.dist-info/top_level.txt
