Metadata-Version: 2.0
Name: django-lair
Version: 1.0.3
Summary: Analytics and metrics app to both store and display user actions
Home-page: https://github.com/narfman0/django_lair
Author: Jon Robison
Author-email: narfman0@gmail.com
License: MIT
Keywords: django_lair
Platform: UNKNOWN
Classifier: Development Status :: 3 - Alpha
Classifier: Framework :: Django
Classifier: Framework :: Django :: 1.8
Classifier: Framework :: Django :: 1.9
Classifier: Framework :: Django :: 1.10
Classifier: Intended Audience :: Developers
Classifier: License :: OSI Approved :: BSD License
Classifier: Natural Language :: English
Classifier: Programming Language :: Python :: 2
Classifier: Programming Language :: Python :: 2.7
Classifier: Programming Language :: Python :: 3
Classifier: Programming Language :: Python :: 3.5
